<annotation>
	<folder>collectedimages</folder>
	<filename>S_3622.png</filename>
	<path>C:\Users\oleel\Code-master-folder\Other\pythonProject5\RealTimeObjectDetection\Tensorflow\workspace\images\collectedimages\S_3622.png</path>
	<source>
		<database>Unknown</database>
	</source>
	<size>
		<width>256</width>
		<height>256</height>
		<depth>3</depth>
	</size>
	<segmented>0</segmented>
	<object>
		<name>S</name>
		<pose>Unspecified</pose>
		<truncated>0</truncated>
		<difficult>0</difficult>
		<bndbox>
			<xmin>165</xmin>
			<ymin>95</ymin>
			<xmax>244</xmax>
			<ymax>180</ymax>
		</bndbox>
	</object>
</annotation>
